xia_easy_proto/__init__.py
xia_easy_proto/proto.cp39-win_amd64.pyd
xia_easy_proto-1.0.9.dist-info/LICENSE.txt
xia_easy_proto-1.0.9.dist-info/METADATA
xia_easy_proto-1.0.9.dist-info/WHEEL
xia_easy_proto-1.0.9.dist-info/top_level.txt
xia_easy_proto-1.0.9.dist-info/RECORD
